{"schools": [{"school_id": "50102728", "school_name": "SD NEGERI 3 TIYINGTALI", "demand": 87, "latitude": -8.4078368, "longitude": 115.6262494, "lunch_time": 570, "cluster": 84, "service_time": 39.8}, {"school_id": "50102733", "school_name": "SD NEGERI 4 ABABI", "demand": 89, "latitude": -8.4033721, "longitude": 115.5964294, "lunch_time": 570, "cluster": 84, "service_time": 40.6}, {"school_id": "50102832", "school_name": "SD NEGERI 7 ABABI", "demand": 78, "latitude": -8.4088219, "longitude": 115.5989522, "lunch_time": 570, "cluster": 84, "service_time": 36.2}, {"school_id": "50102884", "school_name": "SD NEGERI 2 ABABI", "demand": 95, "latitude": -8.4161418, "longitude": 115.604678, "lunch_time": 570, "cluster": 84, "service_time": 43.0}, {"school_id": "50102885", "school_name": "SD NEGERI 2 ABANG", "demand": 137, "latitude": -8.3951902, "longitude": 115.6071143, "lunch_time": 570, "cluster": 84, "service_time": 59.8}, {"school_id": "50102959", "school_name": "SD NEGERI 2 TIYINGTALI", "demand": 144, "latitude": -8.407151899999999, "longitude": 115.6131706, "lunch_time": 570, "cluster": 84, "service_time": 62.6}, {"school_id": "50103808", "school_name": "SD NEGERI 2 TRIBUANA", "demand": 148, "latitude": -8.3977443, "longitude": 115.6176778, "lunch_time": 570, "cluster": 84, "service_time": 64.2}, {"school_id": "50103809", "school_name": "SD NEGERI 3 TRIBUANA", "demand": 132, "latitude": -8.3939069, "longitude": 115.6188492, "lunch_time": 570, "cluster": 84, "service_time": 57.8}, {"school_id": "50103813", "school_name": "SD NEGERI 4 TRIBUANA", "demand": 89, "latitude": -8.388427799999999, "longitude": 115.6203161, "lunch_time": 570, "cluster": 84, "service_time": 40.6}, {"school_id": "50103814", "school_name": "SD NEGERI 1 TIYINGTALI", "demand": 124, "latitude": -8.41403, "longitude": 115.61695, "lunch_time": 570, "cluster": 84, "service_time": 54.6}], "kitchens": [{"kitchen_name": "SPPG Karangasem Karangasem Padangkerta 2", "latitude": -8.425523822252433, "longitude": 115.59398778315924, "type": "sppg", "kitchen_id": "5fe2ce4e-cf67-446f-a4cb-118bb4c34e5d", "capacity": 2000, "fixed_cost": 6000000, "maximum_vehicles": 2}, {"kitchen_name": "Martabak MARBUANA 26", "latitude": -8.4337006, "longitude": 115.6141191, "type": "buffet_restaurant", "kitchen_id": "ff47bdf0-1e18-4468-a956-3f260708c77e", "capacity": 2000, "fixed_cost": 6000000, "maximum_vehicles": 2}, {"kitchen_name": "Katering Warung Nasi Campur Mok Luh jape", "latitude": -8.433556099999999, "longitude": 115.600776, "type": "catering_service", "kitchen_id": "2636c6cc-ca3f-44e2-b4e7-2292b19381fd", "capacity": 2000, "fixed_cost": 6000000, "maximum_vehicles": 2}, {"kitchen_name": "SPPG Karangasem Karangasem Padangkerta", "latitude": -8.43603902894372, "longitude": 115.59592493308222, "type": "sppg", "kitchen_id": "b7ca02c6-73e5-46b2-9686-73553055bc17", "capacity": 2000, "fixed_cost": 6000000, "maximum_vehicles": 2}, {"kitchen_name": "Bali Wedding Catering", "latitude": -8.4398469, "longitude": 115.5959134, "type": "catering_service", "kitchen_id": "495a85a4-5499-4c1f-9fe5-e0b0e221092a", "capacity": 2000, "fixed_cost": 6000000, "maximum_vehicles": 2}], "suppliers": [{"supplier_name": "Luluh sate YAYIK", "latitude": -8.399705299999999, "longitude": 115.6099415, "type": "butcher", "ingredient": "meat"}, {"supplier_name": "IKomang Mandira", "latitude": -8.4088729, "longitude": 115.6139326, "type": "market", "ingredient": "vegetables"}, {"supplier_name": "Tiyingtali", "latitude": -8.4090304, "longitude": 115.61402319999998, "type": "butcher", "ingredient": "meat"}, {"supplier_name": "Pasar tiyingtali", "latitude": -8.410432799999999, "longitude": 115.61651059999998, "type": "market", "ingredient": "vegetables"}, {"supplier_name": "Sodagar dare yan bluyun", "latitude": -8.407108299999999, "longitude": 115.6043167, "type": "market", "ingredient": "vegetables"}], "first_echelon_matrix": [[0.0, 1.7, 1.8, 2.3, 6.0, 10.0, 6.7, 8.8, 13.2, 13.1], [1.7, 0.0, 0.0, 0.5, 7.3, 11.4, 4.9, 7.1, 8.5, 8.5], [1.8, 0.0, 0.0, 0.5, 7.4, 11.4, 4.9, 7.1, 8.5, 8.5], [2.3, 0.5, 0.5, 0.0, 7.7, 7.6, 4.4, 6.6, 8.0, 8.0], [6.0, 7.3, 7.4, 7.9, 0.0, 6.5, 5.4, 6.3, 8.2, 9.7], [10.0, 11.4, 11.4, 7.6, 6.5, 0.0, 6.8, 6.0, 3.4, 3.2], [6.6, 4.9, 4.9, 4.4, 5.4, 6.8, 0.0, 2.6, 3.6, 3.6], [8.8, 7.1, 7.1, 6.6, 6.3, 6.0, 2.6, 0.0, 2.7, 2.7], [13.2, 8.5, 8.4, 7.9, 8.2, 3.4, 3.6, 2.7, 0.0, 1.0], [13.1, 8.5, 8.5, 8.0, 9.7, 3.2, 3.6, 2.7, 1.0, 0.0]], "second_echelon_matrix": [[0.0, 6.8, 6.0, 3.4, 3.2, 9.4, 7.4, 8.4, 5.2, 10.3, 11.1, 14.3, 13.9, 13.5, 7.0], [6.8, 0.0, 2.6, 3.6, 3.6, 6.1, 6.7, 5.7, 4.1, 7.6, 5.3, 8.4, 9.6, 11.2, 3.8], [6.0, 2.6, 0.0, 2.7, 2.7, 8.4, 7.6, 6.5, 5.0, 9.9, 7.5, 10.6, 11.8, 19.3, 6.0], [3.4, 3.6, 2.7, 0.0, 1.0, 9.7, 10.6, 11.6, 6.9, 13.5, 8.8, 17.5, 17.1, 16.7, 7.3], [3.2, 3.6, 2.7, 1.0, 0.0, 9.7, 10.5, 11.4, 8.4, 13.4, 8.9, 17.4, 17.0, 16.6, 7.4], [9.4, 6.2, 8.4, 9.8, 9.8, 0.0, 7.9, 8.4, 8.2, 6.4, 4.1, 3.6, 4.8, 6.4, 2.6], [7.4, 6.8, 7.6, 10.6, 10.5, 7.9, 0.0, 1.1, 2.6, 3.1, 3.8, 8.5, 8.1, 7.7, 5.3], [8.4, 5.7, 6.5, 11.6, 11.4, 8.4, 1.1, 0.0, 1.6, 3.6, 4.4, 9.5, 9.1, 8.7, 5.8], [5.2, 4.1, 5.0, 6.9, 8.4, 8.2, 2.6, 1.6, 0.0, 5.1, 5.9, 10.9, 10.6, 10.2, 5.8], [10.3, 7.7, 9.9, 13.5, 13.4, 6.4, 3.1, 3.6, 5.1, 0.0, 2.4, 6.9, 6.5, 6.1, 3.9], [11.1, 5.3, 7.5, 8.9, 8.9, 4.1, 3.8, 4.4, 5.9, 2.4, 0.0, 6.3, 7.5, 11.4, 1.5], [14.3, 8.4, 10.6, 17.5, 17.4, 3.6, 8.5, 9.5, 10.9, 6.9, 6.3, 0.0, 1.4, 3.0, 4.8], [13.9, 9.6, 11.8, 17.1, 17.0, 4.8, 8.1, 9.1, 10.6, 6.5, 7.5, 1.4, 0.0, 2.7, 6.0], [13.5, 11.3, 19.3, 16.7, 16.6, 6.4, 7.7, 8.7, 10.2, 6.1, 9.2, 3.0, 2.7, 0.0, 7.7], [7.0, 3.8, 6.0, 7.4, 7.4, 2.6, 5.3, 5.8, 5.8, 3.9, 1.5, 4.8, 6.0, 7.7, 0.0]], "ingredients": [{"name": "meat", "ratio_tray_to_kg": 0.1}, {"name": "vegetables", "ratio_tray_to_kg": 0.2}], "E1_vehicles": [{"capacity": 800, "variable_cost": 0.7, "fixed_cost": 100000}, {"capacity": 800, "variable_cost": 0.7, "fixed_cost": 100000}, {"capacity": 800, "variable_cost": 0.7, "fixed_cost": 100000}, {"capacity": 800, "variable_cost": 0.7, "fixed_cost": 100000}, {"capacity": 800, "variable_cost": 0.7, "fixed_cost": 100000}], "E2_vehicles": [{"capacity": 1000, "variable_cost": 0.8, "fixed_cost": 289000}, {"capacity": 1000, "variable_cost": 0.8, "fixed_cost": 289000}, {"capacity": 1000, "variable_cost": 0.8, "fixed_cost": 289000}, {"capacity": 1000, "variable_cost": 0.8, "fixed_cost": 289000}, {"capacity": 1000, "variable_cost": 0.8, "fixed_cost": 289000}, {"capacity": 1000, "variable_cost": 0.8, "fixed_cost": 289000}, {"capacity": 1000, "variable_cost": 0.8, "fixed_cost": 289000}, {"capacity": 1000, "variable_cost": 0.8, "fixed_cost": 289000}, {"capacity": 1000, "variable_cost": 0.8, "fixed_cost": 289000}, {"capacity": 1000, "variable_cost": 0.8, "fixed_cost": 289000}]}